<?xml version="1.0" encoding="utf-8"?>
<Defs>
  <!--imperium romanum-->
  <FactionDef ParentName="HellenesBase">
    <defName>AR_Faction_Rome</defName>
    <label>Rome</label>
    <description>This particular Faction appears to be an exact mirror image of Old Earth's ancient Roman Empire, which is now over five thousand years old. Its original incarnation was divided in 395 AD and its western half died in less than a century after that, but Rome technically lasted for another thousand years, finally being ended in 1453 AD. The Romans of Old Earth built one of the largest, longest lasting, and technologically advanced civilizations in Old Earth's classical antiquity, whose legacy has lasted for the rest of human history and continues to impact the language, culture, and societal structure of most of the myriad of human civilizations that exist even now. \n How did an identical, Bronze Age, Roman society form eons after the real deal died? These people claim to have lived here for millennia, something that even the tribesmen on this Rim World have attested to, and no one is sure how they got here or how they managed to preserve the traditions of classical antiquity for this long. \n \n Then, as now, these far-flung Romans think to be the first and only true civilization on this world and believe to be committed to bring their civilization to other people. Normally they're working with simple mechanical tools and fight with ancient weapons like swords and spears. Do not disregard the threat of this civilization, however: their soldiers are more powerful than they look, wield shields that deflect any melee weapon to this day, and in large numbers, they can still destroy an entire colony in a day.</description>
    <categoryTag>Tribal</categoryTag>
    <pawnsPlural>Romans</pawnsPlural>
    <pawnSingular>Roman</pawnSingular>
    <listOrderPriority>30</listOrderPriority>
    <settlementGenerationWeight>1</settlementGenerationWeight>
    <requiredCountAtGameStart>1</requiredCountAtGameStart>
    <maxConfigurableAtWorldCreation>1</maxConfigurableAtWorldCreation>
    <canMakeRandomly>true</canMakeRandomly>
    <canSiege>true</canSiege>
    <canStageAttacks>true</canStageAttacks>
    <leaderTitle>imperator</leaderTitle>
    <factionIconPath>Icon/Lupa</factionIconPath>
    <colorSpectrum>
		<li>(249,241,222)</li>
		<li>(255,235,122)</li>
		<li>(180,173,150)</li>
		<li>(183,122,61)</li>
    </colorSpectrum>
    <factionNameMaker>NamerFactionRome</factionNameMaker>
    <settlementNameMaker>NamerSettlementRome</settlementNameMaker>
    <techLevel>Neolithic</techLevel>
    <backstoryFilters>
      <li MayRequire="shavius.classical.flavour">
        <categories>
          <li MayRequire="shavius.classical.flavour">Classical</li>
        </categories>
        <commonality>1</commonality>
      </li>
      <li>
        <categories>
          <li>Tribal</li>
        </categories>
        <commonality>0.5</commonality>
      </li>
      <li>
        <categories>
          <li>ImperialCommon</li>
        </categories>
        <commonality>0.05</commonality>
      </li>
      <li>
        <categories>
          <li>ImperialFighter</li>
        </categories>
        <commonality>0.1</commonality>
      </li>
    </backstoryFilters>
    <!-- <geneticVariance>0.4</geneticVariance> -->
    <allowedCultures Inherit="False">
      <li>Romulus</li>
    </allowedCultures>
    <caravanTraderKinds>
      <li>Caravan_Neolithic_BulkGoods</li>
      <li>Caravan_Neolithic_WarMerchant</li>
      <li>Caravan_Neolithic_Slaver</li>
      <li MayRequire="OskarPotocki.VanillaFactionsExpanded.MedievalModule">VFEM_Caravan_Medieval_WineMerchant</li>
    </caravanTraderKinds>
    <visitorTraderKinds>
      <li>Visitor_Neolithic_Standard</li>
    </visitorTraderKinds>
    <baseTraderKinds>
      <li>Base_Neolithic_Standard</li>
      <li MayRequire="sasha.legionaryequipment">Base_Roman_Standard</li>
    </baseTraderKinds>
    <allowedArrivalTemperatureRange>
      <min>-5</min>
      <max>55</max>
    </allowedArrivalTemperatureRange>
    <maxPawnCostPerTotalPointsCurve>
      <points>
        <li>(0,200)</li>
        <li>(70, 225)</li>
        <li>(700, 275)</li>
        <li>(1300, 300)</li>
        <li>(100000, 10000)</li>
      </points>
    </maxPawnCostPerTotalPointsCurve>
    <requiredMemes>
      <li MayRequire="Ludeon.Rimworld.Ideology">Supremacist</li>
      <li MayRequire="Ludeon.Rimworld.Ideology">Collectivist</li>
      <!-- If you have the Mod -->
      <!-- <li MayRequire="VanillaExpanded.VMemesE">VME_Cultured</li> -->
      <li MayRequire="VanillaExpanded.VMemesE">VME_PartyLife</li>
    </requiredMemes>
    <disallowedMemes>
      <li MayRequire="Ludeon.RimWorld.Ideology">Structure_Ideological</li>
	  <li MayRequire="Ludeon.RimWorld.Ideology">Guilty</li>
      <!-- Forbidden Mod Memes -->
      <li MayRequire="llunak.MorePrecepts">Pacifism</li>
      <li MayRequire="Qux.factionhippie">PeaceLove</li>
      <li MayRequire="Zezz.Altrumeme">Altruism</li>
      <li MayRequire="VanillaExpanded.VMemesE">VME_Pacifist</li>
      <li MayRequire="Sarg.AlphaMemes">AM_NonViolence</li>
      <li MayRequire="FalloutRedScare.FalloutRedScare">FRS_Structure_Socialist</li>
      <li MayRequire="SZ.TW.New.GuoHun,Ludeon.RimWorld.Ideology">SZ_Structure_CultureQiYuan</li>
      <li MayRequire="VanillaExpanded.VMemesE">VME_Structure_Corporate</li>
      <li MayRequire="VanillaExpanded.VMemesE">VME_Structure_Agnosticism</li>
      <li MayRequire="erdelf.HumanoidAlienRaces,Ludeon.RimWorld.Ideology">HAR_Xenophilia</li>
    </disallowedMemes>
    <disallowedPrecepts>
      <li MayRequire="Ludeon.Rimworld.Ideology">IdeoDiversity_Abhorrent</li>
      <li MayRequire="Ludeon.Rimworld.Ideology">IdeoDiversity_Respected</li>
      <li MayRequire="Ludeon.Rimworld.Ideology">IdeoDiversity_Exalted</li>
      <li MayRequire="martinbaste.Ideo.XenoPrecept">XenoDiversity_Abhorrent</li>
      <li MayRequire="martinbaste.Ideo.XenoPrecept">XenoDiversity_Horrible</li>
      <li MayRequire="martinbaste.Ideo.XenoPrecept">XenoDiversity_Disapproved</li>
      <li MayRequire="martinbaste.Ideo.XenoPrecept">XenoDiversity_Standard</li>
    </disallowedPrecepts>
    <pawnGroupMakers>
      <li>
        <kindDef>Peaceful</kindDef>
        <options>
          <AR_Citizen>100</AR_Citizen>
          <TSP_AR_CitizenGirl>95</TSP_AR_CitizenGirl>
          <AR_Councilman>20</AR_Councilman>
          <AR_Sagittarius>30</AR_Sagittarius>
          <AR_Hastatus>30</AR_Hastatus>
          <AR_Legionary>50</AR_Legionary>
          <AR_Hoplite>30</AR_Hoplite>
          <AR_HopliteHeavy>10</AR_HopliteHeavy>
          <AR_General>1</AR_General>
          <VFEC_RepublicVillager MayRequire="oskarpotocki.fge.classical">20</VFEC_RepublicVillager>
          <VFEC_Legionnaire MayRequire="oskarpotocki.fge.classical">15</VFEC_Legionnaire>
          <VFEC_RepublicSenator MayRequire="oskarpotocki.fge.classical">7</VFEC_RepublicSenator>
          <VFEC_ScorpionOperator MayRequire="oskarpotocki.vfe.classical">5</VFEC_ScorpionOperator>
          <TSP_AR_Aquilifer MayRequire="sasha.legionaryequipment">2</TSP_AR_Aquilifer>
          <TSP_AR_Legate>3</TSP_AR_Legate>
        </options>
      </li>
      <li>
        <kindDef>Combat</kindDef>
        <options>
          <AR_Citizen>20</AR_Citizen>
          <AR_Hastatus>250</AR_Hastatus>
          <AR_Councilman>50</AR_Councilman>
          <AR_Sagittarius>300</AR_Sagittarius>
          <AR_Triarius>100</AR_Triarius>
          <AR_General>1</AR_General>
          <TSP_AR_Legate>50</TSP_AR_Legate>
          <AR_Legionary>250</AR_Legionary>
          <VFEC_RepublicVillager MayRequire="oskarpotocki.fge.classical">1</VFEC_RepublicVillager>
          <VFEC_Legionnaire MayRequire="oskarpotocki.fge.classical">90</VFEC_Legionnaire>
          <VFEC_ScorpionOperator MayRequire="oskarpotocki.vfe.classical">30</VFEC_ScorpionOperator>
          <TSP_AR_Aquilifer MayRequire="sasha.legionaryequipment">5</TSP_AR_Aquilifer>
          <AR_Hoplite>200</AR_Hoplite>
          <AR_HopliteHeavy>110</AR_HopliteHeavy>
          <Slave>200</Slave>
        </options>
      </li>
      <li>
        <kindDef>Combat</kindDef>
        <options>
          <Slave>10</Slave>
          <AR_Citizen>1</AR_Citizen>
          <AR_Preatorian>50</AR_Preatorian>
          <AR_Legionary>250</AR_Legionary>
          <AR_Centurion>60</AR_Centurion>
          <AR_Hoplite>40</AR_Hoplite>
          <AR_HopliteHeavy>80</AR_HopliteHeavy>
          <VFEC_Legionnaire MayRequire="oskarpotocki.vfe.classical">60</VFEC_Legionnaire>
          <VFEC_Centurion MayRequire="oskarpotocki.vfe.classical">60</VFEC_Centurion>
          <TSP_AR_Legate>50</TSP_AR_Legate>
          <TSP_AR_Aquilifer MayRequire="sasha.legionaryequipment">10</TSP_AR_Aquilifer>
          <TSP_AR_Roman_Emperor>10</TSP_AR_Roman_Emperor>
        </options>
      </li>
      <li>
        <kindDef>Trader</kindDef>
        <traders>
          <AR_Trader>1</AR_Trader>
        </traders>
        <carriers>
          <Muffalo>5</Muffalo>
          <Dromedary>5</Dromedary>
          <Alpaca>2</Alpaca>
          <Elephant>2</Elephant>
        </carriers>
        <guards>
          <AR_Citizen>100</AR_Citizen>
          <TSP_AR_CitizenGirl>55</TSP_AR_CitizenGirl>
          <AR_Councilman>10</AR_Councilman>
          <VFEC_RepublicSenator MayRequire="oskarpotocki.fge.classical">10</VFEC_RepublicSenator>
          <AR_Hastatus>275</AR_Hastatus>
          <AR_Sagittarius>300</AR_Sagittarius>
          <AR_Triarius>40</AR_Triarius>
          <AR_Preatorian>20</AR_Preatorian>
          <AR_Centurion>40</AR_Centurion>
          <AR_Legionary>300</AR_Legionary>
          <AR_Hoplite>200</AR_Hoplite>
          <AR_HopliteHeavy>200</AR_HopliteHeavy>
          <VFEC_Legionnaire MayRequire="oskarpotocki.vfe.classical">100</VFEC_Legionnaire>
          <TSP_AR_Aquilifer MayRequire="sasha.legionaryequipment">5</TSP_AR_Aquilifer>
          <Slave>2</Slave>
        </guards>
      </li>
      <li>
        <kindDef>Settlement</kindDef>
        <options>
          <VFEC_RepublicVillager MayRequire="oskarpotocki.fge.classical">100</VFEC_RepublicVillager>
          <AR_Citizen>500</AR_Citizen>
          <AR_Preatorian>100</AR_Preatorian>
          <AR_Hastatus>150</AR_Hastatus>
          <AR_Councilman>80</AR_Councilman>
          <VFEC_RepublicSenator MayRequire="oskarpotocki.fge.classical">70</VFEC_RepublicSenator>
          <AR_Sagittarius>200</AR_Sagittarius>
          <AR_Triarius>50</AR_Triarius>
          <AR_Centurion>100</AR_Centurion>
          <AR_Legionary>250</AR_Legionary>
          <AR_General>50</AR_General>
          <TSP_AR_Legate>50</TSP_AR_Legate>
          <TSP_AR_CitizenGirl>500</TSP_AR_CitizenGirl>
          <TSP_AR_Roman_Emperor>25</TSP_AR_Roman_Emperor>
          <AR_Hoplite>300</AR_Hoplite>
          <AR_HopliteHeavy>130</AR_HopliteHeavy>
          <!-- <Slave>150</Slave> -->
          <VFEC_Legionnaire MayRequire="oskarpotocki.vfe.classical">140</VFEC_Legionnaire>
          <TSP_AR_Aquilifer MayRequire="sasha.legionaryequipment">5</TSP_AR_Aquilifer>
        </options>
      </li>
    </pawnGroupMakers>
    <modExtensions>
        <li Class="KCSG.CustomGenOption" MayRequire="oskarpotocki.vfe.classical,oskarpotocki.vanillafactionsexpanded.core">
          <chooseFromlayouts MayRequire="oskarpotocki.vfe.classical,oskarpotocki.vanillafactionsexpanded.core">
            <li MayRequire="oskarpotocki.vfe.classical,oskarpotocki.vanillafactionsexpanded.core">VFEC_ClassicalSettlement1</li>
          </chooseFromlayouts>
        </li>
    </modExtensions>
    <leaderForceGenerateNewPawn>true</leaderForceGenerateNewPawn>
    <fixedLeaderKinds Inherit="False">
      <li>TSP_AR_Roman_Emperor</li>
    </fixedLeaderKinds>
    <settlementTexturePath>Icon/FactionBase/ClassicalAntiquityFactionBase</settlementTexturePath>
  </FactionDef>
</Defs>
